slackly/__init__.py
slackly/compat.py
slackly/config.py
slackly/oauth_utils.py
slackly/scopes.py
slackly/api/__init__.py
slackly/api/endpoints/__init__.py
slackly/api/endpoints/_base.py
slackly/api/endpoints/api.py
slackly/api/endpoints/auth.py
slackly/api/endpoints/bots.py
slackly/api/endpoints/channels.py
slackly/api/endpoints/chat.py
slackly/api/endpoints/dnd.py
slackly/api/endpoints/emoji.py
slackly/api/endpoints/files.py
slackly/api/endpoints/groups.py
slackly/api/endpoints/im.py
slackly/api/endpoints/mpim.py
slackly/api/endpoints/oauth.py
slackly/api/endpoints/pins.py
slackly/api/endpoints/reactions.py
slackly/api/endpoints/reminders.py
slackly/api/endpoints/rtm.py
slackly/api/endpoints/search.py
slackly/api/endpoints/stars.py
slackly/api/endpoints/team.py
slackly/api/endpoints/usergroups.py
slackly/api/endpoints/users.py
slackly/client/__init__.py
slackly/client/api_client.py
slackly/client/rtm_client.py
slackly/client/event_factory/__init__.py
slackly/client/response_factory/__init__.py
slackly/events/__init__.py
slackly/events/_base.py
slackly/events/accounts_changed.py
slackly/events/bot_added.py
slackly/events/bot_changed.py
slackly/events/channel_archive.py
slackly/events/channel_created.py
slackly/events/channel_deleted.py
slackly/events/channel_history_changed.py
slackly/events/channel_joined.py
slackly/events/channel_left.py
slackly/events/channel_marked.py
slackly/events/channel_rename.py
slackly/events/channel_unarchive.py
slackly/events/commands_changed.py
slackly/events/desktop_notification.py
slackly/events/dnd_updated.py
slackly/events/dnd_updated_user.py
slackly/events/email_domain_changed.py
slackly/events/emoji_changed.py
slackly/events/file_change.py
slackly/events/file_comment_added.py
slackly/events/file_comment_deleted.py
slackly/events/file_comment_edited.py
slackly/events/file_created.py
slackly/events/file_deleted.py
slackly/events/file_public.py
slackly-1.0.7.dist-info/DESCRIPTION.rst
slackly-1.0.7.dist-info/METADATA
slackly-1.0.7.dist-info/RECORD
slackly-1.0.7.dist-info/WHEEL
slackly-1.0.7.dist-info/metadata.json
slackly-1.0.7.dist-info/top_level.txt
slackly-1.0.7.dist-info/zip-safe
